ecfr/__init__.py
ecfr/ecfr.py
ecfr/example/conf.json
ecfr/example/starter_files/starter.py
ecfr-0.1.1.dist-info/LICENSE
ecfr-0.1.1.dist-info/METADATA
ecfr-0.1.1.dist-info/WHEEL
ecfr-0.1.1.dist-info/entry_points.txt
ecfr-0.1.1.dist-info/RECORD
