Metadata-Version: 2.1
Name: ecfr
Version: 0.1.1
Summary: A package to make CodeForces contests easier.
License: MIT
Author: Eliot Robson
Author-email: eliot.robson24@gmail.com
Requires-Python: >=3.9
Classifier: License :: OSI Approved :: MIT License
Classifier: Programming Language :: Python :: 3
Classifier: Programming Language :: Python :: 3.9
Classifier: Programming Language :: Python :: 3.10
Classifier: Programming Language :: Python :: 3.11
Classifier: Programming Language :: Python :: 3.12
Requires-Dist: beautifulsoup4 (>=4)
Requires-Dist: click (>=8)
Requires-Dist: colorama (>=0.4)
Requires-Dist: lxml (>=4)
Requires-Dist: requests (>=2)
Project-URL: changelog, https://github.com/eliotwrobson/CodeforcesRunnerEliot/releases
Project-URL: documentation, https://github.com/eliotwrobson/CodeforcesRunnerEliot#readme
Project-URL: homepage, https://github.com/eliotwrobson/CodeforcesRunnerEliot
Project-URL: repository, https://github.com/eliotwrobson/CodeforcesRunnerEliot
